paymob/__init__.py
paymob/accept/__init__.py
paymob/accept/accept_client.py
paymob/accept/config.py
paymob/accept/connection.py
paymob/accept/constants.py
paymob/accept/factories.py
paymob/accept/hmac_validator.py
paymob/accept/response_codes.py
paymob/accept/transaction.py
paymob/accept/utils.py
paymob/accept/callbacks/__init__.py
paymob/accept/callbacks/card_token_callback.py
paymob/accept/callbacks/delivery_status_callback.py
paymob/accept/callbacks/generic_callback.py
paymob/accept/callbacks/transaction_callback.py
paymob/accept/data_classes/__init__.py
paymob/accept/data_classes/data.py
paymob/accept/data_classes/merchant.py
paymob/accept/data_classes/order.py
paymob/accept/data_classes/order_item.py
paymob/accept/data_classes/payment_key_claims.py
paymob/accept/data_classes/shipping_data.py
paymob/accept/data_classes/source_data.py
paymob/accept/data_classes/transaction.py
paymob/data_classes/__init__.py
paymob/data_classes/response_feedback_dataclass.py
paymob/utils/__init__.py
paymob/utils/class_factory.py
tests/__init__.py
tests/utils.py
tests/accept/__init__.py
tests/accept/test_accept_utils_class.py
tests/accept/test_hmac_validator.py
Paymob_Toolbox-0.0.2.dist-info/METADATA
Paymob_Toolbox-0.0.2.dist-info/WHEEL
Paymob_Toolbox-0.0.2.dist-info/top_level.txt
Paymob_Toolbox-0.0.2.dist-info/RECORD
