Metadata-Version: 2.1
Name: Paymob-Toolbox
Version: 0.0.2
Summary: A simple Python package that provides convenient access to the Paymob APIs from applications written in the Python language.
Home-page: https://github.com/muhammedattif/Paymob
Author: DjangoFam Team
Author-email: mahmoud.nasser.abdulhamed11@gmail.com
License: UNKNOWN
Keywords: pypi,paymob,payment,python
Platform: UNKNOWN
Classifier: Development Status :: 1 - Planning
Classifier: Intended Audience :: Developers
Classifier: Programming Language :: Python :: 3
Classifier: Operating System :: Unix
Classifier: Operating System :: MacOS :: MacOS X
Classifier: Operating System :: Microsoft :: Windows
